sem3/sck/forAlu/MODEL/top.v
module ALU #(
    parameter WIDTH = 8
)
(
    input wire signed [WIDTH-1:0] i_arg0,
    input wire signed [WIDTH-1:0] i_arg1,
    input wire [1:0] i_oper,

    input wire i_CLK,
    input wire i_RSTn,

    output reg [WIDTH-1:0] o_result, 
    output reg [2:0] o_flag
);

    reg [WIDTH-1:0] next_result;
    reg [2:0] next_flag;
    
    reg [WIDTH:0] temp_add_sub;
    reg [2*WIDTH-1:0] temp_vec;
    integer i;

    always @(*) begin
        next_result = {WIDTH{1'b0}};
        next_flag = 3'b000;
        temp_add_sub = {(WIDTH+1){1'b0}};
        temp_vec = {(2*WIDTH){1'b0}};

        case(i_oper)
            2'b00: begin
                temp_add_sub = i_arg0 + i_arg1;
                next_result  = temp_add_sub[WIDTH-1:0];
                
                next_flag[1] = temp_add_sub[WIDTH];
                
                next_flag[0] = (i_arg0[WIDTH-1] == i_arg1[WIDTH-1]) && (next_result[WIDTH-1] != i_arg0[WIDTH-1]);
            end

            2'b01: begin
                {next_flag[1], next_result} = $unsigned(i_arg0) - $unsigned(i_arg1);
                
                next_flag[0] = (i_arg0[WIDTH-1] != i_arg1[WIDTH-1]) && (next_result[WIDTH-1] != i_arg0[WIDTH-1]);
            end

            2'b10: begin
                next_result = i_arg0 & i_arg1;
            end

            2'b11: begin
                temp_vec = {i_arg1, i_arg0};
                next_result = 0;
                for(i = 0; i < 2*WIDTH; i = i + 1)
                    next_result = next_result + temp_vec[i];
                
            end
            
            default: begin
                next_result = {WIDTH{1'b0}};
            end
        endcase

        next_flag[2] = (next_result == {WIDTH{1'b0}});
    end

    always @(posedge i_CLK or negedge i_RSTn) begin
        if (!i_RSTn) begin
            o_result <= {WIDTH{1'b0}};
            o_flag <= 3'b000;
        end
        else begin
            o_result <= next_result;
            o_flag <= next_flag;
        end
    end

endmodule

sem3/sck/forAlu/TESTBENCH/simulation_modules.v
module global_signals 
    #(
        parameter SIM_CLOCK_CYCLES = 120,
        parameter CLOCK_PERIOD = 10,
        parameter SIGNAL_VCD_FILE = "SIGNALS.vcd"
    )
    (
        output wire o_CLK,
        output wire o_RSTn
    );
        
        reg clk;
        reg rst_n;

        assign o_CLK = clk;
        assign o_RSTn = rst_n;

        localparam CLK_PERIOD = CLOCK_PERIOD;
        always #(CLK_PERIOD/2) 
            clk=~clk;

        initial begin
            $dumpfile(SIGNAL_VCD_FILE);
            $dumpvars(0, testbench);
        end

        initial begin
            #1;
            rst_n<=1'bx; clk<=1'bx;
            
            #(CLK_PERIOD*3) rst_n<=1;
            
            #(CLK_PERIOD*3) rst_n<=0;clk<=0;
            
            repeat(5) 
                @(posedge clk);
            
            rst_n<=1;
            @(posedge clk);

            repeat(SIM_CLOCK_CYCLES) 
                @(posedge clk);

            $finish;
        end
endmodule

module random_vector
    #(
        parameter WIDTH = 9
    ) 
    (
        input  wire i_CLK,
        input  wire i_RSTn,
        input  wire i_READY,
        output wire o_VALID,
        output wire [WIDTH-1 : 0] o_Y
    );
        integer SEED = 100;
        reg s_was_valid;
        reg [WIDTH-1 : 0] s_Y;
        reg s_VALID;

        assign #(1) o_Y     = s_Y;
        assign #(1) o_VALID = s_VALID;

        initial 
        begin
            #1;
            @(posedge i_RSTn);

            s_Y <= {WIDTH{1'b0}};
            s_VALID <= 1'b0;
            s_was_valid <= 1'b0;

            forever 
            begin
                fork 
                    begin : GENEROWANIE_SYGNALOW_WYJSCIOWYCH
                        @(posedge i_CLK)
                        begin
                            s_VALID <= $random(SEED);
                            if (i_READY == 1'b1 && s_was_valid == 1'b1)
                                {s_Y} <= {s_Y, $random(SEED)};
                        end
                        
                        if (i_RSTn == 1'b0)
                            @(posedge i_RSTn);
                    end

                    begin : ZAPAMIETANIE_POPRZEDNIEGO_VALID
                        @(negedge i_CLK)
                            s_was_valid <= s_VALID;
                    end
                join
            end
        end
endmodule

sem3/sck/forAlu/TESTBENCH/testbench.v
`timescale 1ns / 1ps

module testbench;

    localparam DATA_WIDTH = 8;
    wire s_CLK, s_RSTn;

    wire signed [DATA_WIDTH-1:0] w_rand_A;
    wire signed [DATA_WIDTH-1:0] w_rand_B;
    reg  [1:0] r_oper;
    
    wire signed [DATA_WIDTH-1:0] w_result;
    wire [2:0] w_flags;

    reg r_test_enable;

    global_signals #(.SIM_CLOCK_CYCLES(150), .CLOCK_PERIOD(10), .SIGNAL_VCD_FILE("alu_stage1.vcd"))
        U_RST_CLK (.o_CLK(s_CLK), .o_RSTn(s_RSTn));
    
    reg signed [DATA_WIDTH-1:0] r_gen_A, r_gen_B;

    always @(posedge s_CLK or negedge s_RSTn) begin
        if (!s_RSTn) begin
            r_gen_A <= {DATA_WIDTH{1'b0}};
            r_gen_B <= {DATA_WIDTH{1'b0}};
        end else if (r_test_enable) begin
            r_gen_A <= $random;
            r_gen_B <= $random;
        end
    end
    
    assign w_rand_A = r_gen_A;
    assign w_rand_B = r_gen_B;

    ALU #(
        .WIDTH(DATA_WIDTH)
    ) UTOP (
        .i_CLK(s_CLK),
        .i_RSTn(s_RSTn),
        
        .i_arg0(w_rand_A), 
        .i_arg1(w_rand_B),
        .i_oper(r_oper),
        
        .o_result(w_result),
        .o_flag(w_flags)
    );
    
    initial begin
        r_oper = 2'b00;
        r_test_enable = 0;
        
        wait(s_RSTn == 0);
        wait(s_RSTn == 1);
        @(posedge s_CLK); 
        
        r_test_enable = 1;

        r_oper <= 2'b00;
        repeat(20) @(posedge s_CLK);

        r_oper <= 2'b01;
        repeat(20) @(posedge s_CLK);

        r_oper <= 2'b10;
        repeat(20) @(posedge s_CLK);

        r_oper <= 2'b11;
        repeat(20) @(posedge s_CLK);

        r_test_enable = 0;
        repeat(5) @(posedge s_CLK);
        
        $finish; 
    end

endmodule

sem3/sck/forAlu/WORK/alu_stage1.vcd
$date
	Tue Jan 20 09:41:21 2026
$end
$version
	Icarus Verilog
$end
$timescale
	1ps
$end
$scope module testbench $end
$var wire 8 ! w_rand_A [7:0] $end
$var wire 8 " w_rand_B [7:0] $end
$var wire 8 # w_result [7:0] $end
$var wire 3 $ w_flags [2:0] $end
$var wire 1 % s_RSTn $end
$var wire 1 & s_CLK $end
$var reg 8 ' r_gen_A [7:0] $end
$var reg 8 ( r_gen_B [7:0] $end
$var reg 2 ) r_oper [1:0] $end
$var reg 1 * r_test_enable $end
$scope module UTOP $end
$var wire 8 + i_arg0 [7:0] $end
$var wire 8 , i_arg1 [7:0] $end
$var wire 2 - i_oper [1:0] $end
$var wire 1 % i_RSTn $end
$var wire 1 & i_CLK $end
$var reg 3 . next_flag [2:0] $end
$var reg 8 / next_result [7:0] $end
$var reg 3 0 o_flag [2:0] $end
$var reg 8 1 o_result [7:0] $end
$var reg 9 2 temp_add_sub [8:0] $end
$var reg 16 3 temp_vec [15:0] $end
$var integer 32 4 i [31:0] $end
$upscope $end
$scope module U_RST_CLK $end
$var wire 1 & o_CLK $end
$var wire 1 % o_RSTn $end
$var reg 1 5 clk $end
$var reg 1 6 rst_n $end
$upscope $end
$upscope $end
$enddefinitions $end
#0
$dumpvars
x6
x5
bx 4
b0 3
bx 2
bx 1
bx 0
bx /
bx .
b0 -
bx ,
bx +
0*
b0 )
bx (
bx '
x&
x%
bx $
bx #
bx "
bx !
$end
#31000
1%
16
#61000
b0 2
b100 .
b0 /
b0 $
b0 0
b0 #
b0 1
b0 "
b0 ,
b0 (
b0 !
b0 +
b0 '
0&
05
0%
06
#65000
1&
15
#70000
0&
05
#75000
1&
15
#80000
0&
05
#85000
1&
15
#90000
0&
05
#95000
1&
15
#100000
0&
05
#105000
1%
16
1&
15
#110000
0&
05
#115000
b100 $
b100 0
1*
1&
15
#120000
0&
05
#125000
b10100101 /
b110100101 2
b10 .
b10000001 "
b10000001 ,
b10000001 (
b100100 !
b100100 +
b100100 '
1&
15
#130000
0&
05
#135000
b1101100 2
b0 .
b1101100 /
b10 $
b10 0
b10100101 #
b10100101 1
b1100011 "
b1100011 ,
b1100011 (
b1001 !
b1001 +
b1001 '
1&
15
#140000
0&
05
#145000
b10 .
b110011010 2
b10011010 /
b10001101 "
b10001101 ,
b10001101 (
b1101 !
b1101 +
b1101 '
b0 $
b0 0
b1101100 #
b1101100 1
1&
15
#150000
0&
05
#155000
b1110111 2
b0 .
b1110111 /
b10 $
b10 0
b10011010 #
b10011010 1
b10010 "
b10010 ,
b10010 (
b1100101 !
b1100101 +
b1100101 '
1&
15
#160000
0&
05
#165000
b1110 2
b1110 /
b1101 "
b1101 ,
b1101 (
b1 !
b1 +
b1 '
b0 $
b0 0
b1110111 #
b1110111 1
1&
15
#170000
0&
05
#175000
b1 .
b10110011 2
b10110011 /
b1110 #
b1110 1
b111101 "
b111101 ,
b111101 (
b1110110 !
b1110110 +
b1110110 '
1&
15
#180000
0&
05
#185000
b101111001 2
b11 .
b1111001 /
b10001100 "
b10001100 ,
b10001100 (
b11101101 !
b11101101 +
b11101101 '
b1 $
b1 0
b10110011 #
b10110011 1
1&
15
#190000
0&
05
#195000
b110111111 2
b10 .
b10111111 /
b11 $
b11 0
b1111001 #
b1111001 1
b11000110 "
b11000110 ,
b11000110 (
b11111001 !
b11111001 +
b11111001 '
1&
15
#200000
0&
05
#205000
b101101111 2
b11 .
b1101111 /
b10101010 "
b10101010 ,
b10101010 (
b11000101 !
b11000101 +
b11000101 '
b10 $
b10 0
b10111111 #
b10111111 1
1&
15
#210000
0&
05
#215000
b1011100 2
b0 .
b1011100 /
b11 $
b11 0
b1101111 #
b1101111 1
b1110111 "
b1110111 ,
b1110111 (
b11100101 !
b11100101 +
b11100101 '
1&
15
#220000
0&
05
#225000
b10 .
b110100001 2
b10100001 /
b10001111 "
b10001111 ,
b10001111 (
b10010 !
b10010 +
b10010 '
b0 $
b0 0
b1011100 #
b1011100 1
1&
15
#230000
0&
05
#235000
b111000000 2
b10 .
b11000000 /
b10 $
b10 0
b10100001 #
b10100001 1
b11001110 "
b11001110 ,
b11001110 (
b11110010 !
b11110010 +
b11110010 '
1&
15
#240000
0&
05
#245000
b110101101 2
b10 .
b10101101 /
b11000101 "
b11000101 ,
b11000101 (
b11101000 !
b11101000 +
b11101000 '
b11000000 #
b11000000 1
1&
15
#250000
0&
05
#255000
b11001 2
b0 .
b11001 /
b10101101 #
b10101101 1
b10111101 "
b10111101 ,
b10111101 (
b1011100 !
b1011100 +
b1011100 '
1&
15
#260000
0&
05
#265000
b1 .
b10010010 2
b10010010 /
b1100101 "
b1100101 ,
b1100101 (
b101101 !
b101101 +
b101101 '
b0 $
b0 0
b11001 #
b11001 1
1&
15
#270000
0&
05
#275000
b1101101 2
b0 .
b1101101 /
b1 $
b1 0
b10010010 #
b10010010 1
b1010 "
b1010 ,
b1010 (
b1100011 !
b1100011 +
b1100011 '
1&
15
#280000
0&
05
#285000
b10 .
b110100000 2
b10100000 /
b100000 "
b100000 ,
b100000 (
b10000000 !
b10000000 +
b10000000 '
b0 $
b0 0
b1101101 #
b1101101 1
1&
15
#290000
0&
05
#295000
b101000111 2
b11 .
b1000111 /
b10 $
b10 0
b10100000 #
b10100000 1
b10011101 "
b10011101 ,
b10011101 (
b10101010 !
b10101010 +
b10101010 '
1&
15
#300000
0&
05
#305000
b110101001 2
b10 .
b10101001 /
b10011 "
b10011 ,
b10011 (
b10010110 !
b10010110 +
b10010110 '
b11 $
b11 0
b1000111 #
b1000111 1
1&
15
#310000
0&
05
#315000
b0 2
b10 .
b10111010 /
b1 )
b1 -
b10 $
b10 0
b10101001 #
b10101001 1
b1010011 "
b1010011 ,
b1010011 (
b1101 !
b1101 +
b1101 '
1&
15
#320000
0&
05
#325000
b11 .
b10010110 /
b11010101 "
b11010101 ,
b11010101 (
b1101011 !
b1101011 +
b1101011 '
b10111010 #
b10111010 1
1&
15
#330000
0&
05
#335000
b10 .
b1010100 /
b11 $
b11 0
b10010110 #
b10010110 1
b10101110 "
b10101110 ,
b10101110 (
b10 !
b10 +
b10 '
1&
15
#340000
0&
05
#345000
b10 .
b1001110 /
b11001111 "
b11001111 ,
b11001111 (
b11101 !
b11101 +
b11101 '
b10 $
b10 0
b1010100 #
b1010100 1
1&
15
#350000
0&
05
#355000
b0 .
b11001 /
b1001110 #
b1001110 1
b1010 "
b1010 ,
b1010 (
b100011 !
b100011 +
b100011 '
1&
15
#360000
0&
05
#365000
b10001110 /
b111100 "
b111100 ,
b111100 (
b11001010 !
b11001010 +
b11001010 '
b0 $
b0 0
b11001 #
b11001 1
1&
15
#370000
0&
05
#375000
b1101000 /
b10001110 #
b10001110 1
b10001010 "
b10001010 ,
b10001010 (
b11110010 !
b11110010 +
b11110010 '
1&
15
#380000
0&
05
#385000
b10 .
b1101001 /
b11011000 "
b11011000 ,
b11011000 (
b1000001 !
b1000001 +
b1000001 '
b1101000 #
b1101000 1
1&
15
#390000
0&
05
#395000
b11 .
b11101111 /
b10 $
b10 0
b1101001 #
b1101001 1
b10001001 "
b10001001 ,
b10001001 (
b1111000 !
b1111000 +
b1111000 '
1&
15
#400000
0&
05
#405000
b0 .
b110101 /
b10110110 "
b10110110 ,
b10110110 (
b11101011 !
b11101011 +
b11101011 '
b11 $
b11 0
b11101111 #
b11101111 1
1&
15
#410000
0&
05
#415000
b11000 /
b0 $
b0 0
b110101 #
b110101 1
b10101110 "
b10101110 ,
b10101110 (
b11000110 !
b11000110 +
b11000110 '
1&
15
#420000
0&
05
#425000
b10010010 /
b101010 "
b101010 ,
b101010 (
b10111100 !
b10111100 +
b10111100 '
b11000 #
b11000 1
1&
15
#430000
0&
05
#435000
b10 .
b10011010 /
b10010010 #
b10010010 1
b1110001 "
b1110001 ,
b1110001 (
b1011 !
b1011 +
b1011 '
1&
15
#440000
0&
05
#445000
b1 .
b110110 /
b1001111 "
b1001111 ,
b1001111 (
b10000101 !
b10000101 +
b10000101 '
b10 $
b10 0
b10011010 #
b10011010 1
1&
15
#450000
0&
05
#455000
b0 .
b1 /
b1 $
b1 0
b110110 #
b110110 1
b111010 "
b111010 ,
b111010 (
b111011 !
b111011 +
b111011 '
1&
15
#460000
0&
05
#465000
b1101001 /
b10101 "
b10101 ,
b10101 (
b1111110 !
b1111110 +
b1111110 '
b0 $
b0 0
b1 #
b1 1
1&
15
#470000
0&
05
#475000
b11000 /
b1101001 #
b1101001 1
b11011001 "
b11011001 ,
b11011001 (
b11110001 !
b11110001 +
b11110001 '
1&
15
#480000
0&
05
#485000
b10110 /
b1001100 "
b1001100 ,
b1001100 (
b1100010 !
b1100010 +
b1100010 '
b11000 #
b11000 1
1&
15
#490000
0&
05
#495000
b10000 /
b10110 #
b10110 1
b10001111 "
b10001111 ,
b10001111 (
b10011111 !
b10011111 +
b10011111 '
1&
15
#500000
0&
05
#505000
b1000001 /
b10110111 "
b10110111 ,
b10110111 (
b11111000 !
b11111000 +
b11111000 '
b10000 #
b10000 1
1&
15
#510000
0&
05
#515000
b11100 /
b10 )
b10 -
b1000001 #
b1000001 1
b1011100 "
b1011100 ,
b1011100 (
b10011111 !
b10011111 +
b10011111 '
1&
15
#520000
0&
05
#525000
b1001 /
b10001001 "
b10001001 ,
b10001001 (
b1011011 !
b1011011 +
b1011011 '
b11100 #
b11100 1
1&
15
#530000
0&
05
#535000
b1000000 /
b1001 #
b1001 1
b11010000 "
b11010000 ,
b11010000 (
b1001001 !
b1001001 +
b1001001 '
1&
15
#540000
0&
05
#545000
b1010001 /
b1010001 "
b1010001 ,
b1010001 (
b11010111 !
b11010111 +
b11010111 '
b1000000 #
b1000000 1
1&
15
#550000
0&
05
#555000
b100 /
b1010001 #
b1010001 1
b1100 "
b1100 ,
b1100 (
b10010110 !
b10010110 +
b10010110 '
1&
15
#560000
0&
05
#565000
b11000000 /
b11001000 "
b11001000 ,
b11001000 (
b11000010 !
b11000010 +
b11000010 '
b100 #
b100 1
1&
15
#570000
0&
05
#575000
b110101 /
b11000000 #
b11000000 1
b111101 "
b111101 ,
b111101 (
b1110111 !
b1110111 +
b1110111 '
1&
15
#580000
0&
05
#585000
b10010 /
b1111110 "
b1111110 ,
b1111110 (
b10010 !
b10010 +
b10010 '
b110101 #
b110101 1
1&
15
#590000
0&
05
#595000
b101001 /
b10010 #
b10010 1
b111001 "
b111001 ,
b111001 (
b1101101 !
b1101101 +
b1101101 '
1&
15
#600000
0&
05
#605000
b10011 /
b11010011 "
b11010011 ,
b11010011 (
b11111 !
b11111 +
b11111 '
b101001 #
b101001 1
1&
15
#610000
0&
05
#615000
b100 .
b0 /
b10011 #
b10011 1
b1111000 "
b1111000 ,
b1111000 (
b10000101 !
b10000101 +
b10000101 '
1&
15
#620000
0&
05
#625000
b1001001 /
b0 .
b1001001 "
b1001001 ,
b1001001 (
b1011011 !
b1011011 +
b1011011 '
b100 $
b100 0
b0 #
b0 1
1&
15
#630000
0&
05
#635000
b101010 /
b0 $
b0 0
b1001001 #
b1001001 1
b101010 "
b101010 ,
b101010 (
b111111 !
b111111 +
b111111 '
1&
15
#640000
0&
05
#645000
b100 .
b0 /
b10000110 "
b10000110 ,
b10000110 (
b1011000 !
b1011000 +
b1011000 '
b101010 #
b101010 1
1&
15
#650000
0&
05
#655000
b10001100 /
b0 .
b100 $
b100 0
b0 #
b0 1
b10011100 "
b10011100 ,
b10011100 (
b10001110 !
b10001110 +
b10001110 '
1&
15
#660000
0&
05
#665000
b100010 /
b100110 "
b100110 ,
b100110 (
b11111010 !
b11111010 +
b11111010 '
b0 $
b0 0
b10001100 #
b10001100 1
1&
15
#670000
0&
05
#675000
b100011 /
b100010 #
b100010 1
b10100011 "
b10100011 ,
b10100011 (
b1110011 !
b1110011 +
b1110011 '
1&
15
#680000
0&
05
#685000
b100011 /
b10110011 "
b10110011 ,
b10110011 (
b101111 !
b101111 +
b101111 '
b100011 #
b100011 1
1&
15
#690000
0&
05
#695000
b1000100 /
b1000100 "
b1000100 ,
b1000100 (
b1011111 !
b1011111 +
b1011111 '
1&
15
#700000
0&
05
#705000
b11000011 /
b11001011 "
b11001011 ,
b11001011 (
b11110111 !
b11110111 +
b11110111 '
b1000100 #
b1000100 1
1&
15
#710000
0&
05
#715000
b10000 4
b101101011100110 3
b1001 /
b11 )
b11 -
b11000011 #
b11000011 1
b1011010 "
b1011010 ,
b1011010 (
b11100110 !
b11100110 +
b11100110 '
1&
15
#720000
0&
05
#725000
b10000 4
b1110110100101001 3
b1001 /
b11101101 "
b11101101 ,
b11101101 (
b101001 !
b101001 +
b101001 '
b1001 #
b1001 1
1&
15
#730000
0&
05
#735000
b10000 4
b110010111011010 3
b1001 /
b1100101 "
b1100101 ,
b1100101 (
b11011010 !
b11011010 +
b11011010 '
1&
15
#740000
0&
05
#745000
b10000 4
b1101111110110101 3
b1100 /
b11011111 "
b11011111 ,
b11011111 (
b10110101 !
b10110101 +
b10110101 '
1&
15
#750000
0&
05
#755000
b10000 4
b100010001111001 3
b111 /
b1100 #
b1100 1
b1000100 "
b1000100 ,
b1000100 (
b1111001 !
b1111001 +
b1111001 '
1&
15
#760000
0&
05
#765000
b10000 4
b10101011010000 3
b110 /
b101010 "
b101010 ,
b101010 (
b11010000 !
b11010000 +
b11010000 '
b111 #
b111 1
1&
15
#770000
0&
05
#775000
b10000 4
b111010101011 3
b1000 /
b110 #
b110 1
b1110 "
b1110 ,
b1110 (
b10101011 !
b10101011 +
b10101011 '
1&
15
#780000
0&
05
#785000
b10000 4
b1001101011011100 3
b1001 /
b10011010 "
b10011010 ,
b10011010 (
b11011100 !
b11011100 +
b11011100 '
b1000 #
b1000 1
1&
15
#790000
0&
05
#795000
b10000 4
b1100001111111101 3
b1011 /
b1001 #
b1001 1
b11000011 "
b11000011 ,
b11000011 (
b11111101 !
b11111101 +
b11111101 '
1&
15
#800000
0&
05
#805000
b10000 4
b100111001010110 3
b1000 /
b1001110 "
b1001110 ,
b1001110 (
b1010110 !
b1010110 +
b1010110 '
b1011 #
b1011 1
1&
15
#810000
0&
05
#815000
b10000 4
b101001100111 3
b111 /
b1000 #
b1000 1
b1010 "
b1010 ,
b1010 (
b1100111 !
b1100111 +
b1100111 '
1&
15
#820000
0&
05
#825000
b10000 4
b11100010110110 3
b1000 /
b111000 "
b111000 ,
b111000 (
b10110110 !
b10110110 +
b10110110 '
b111 #
b111 1
1&
15
#830000
0&
05
#835000
b10000 4
b1011100001111001 3
b1001 /
b1000 #
b1000 1
b10111000 "
b10111000 ,
b10111000 (
b1111001 !
b1111001 +
b1111001 '
1&
15
#840000
0&
05
#845000
b10000 4
b1001001110010100 3
b111 /
b10010011 "
b10010011 ,
b10010011 (
b10010100 !
b10010100 +
b10010100 '
b1001 #
b1001 1
1&
15
#850000
0&
05
#855000
b10000 4
b101100100000100 3
b101 /
b111 #
b111 1
b1011001 "
b1011001 ,
b1011001 (
b100 !
b100 +
b100 '
1&
15
#860000
0&
05
#865000
b10000 4
b100110111011011 3
b1010 /
b1001101 "
b1001101 ,
b1001101 (
b11011011 !
b11011011 +
b11011011 '
b101 #
b101 1
1&
15
#870000
0&
05
#875000
b10000 4
b110110111011001 3
b1010 /
b1010 #
b1010 1
b1101101 "
b1101101 ,
b1101101 (
b11011001 !
b11011001 +
b11011001 '
1&
15
#880000
0&
05
#885000
b10000 4
b1100101001110110 3
b1001 /
b11001010 "
b11001010 ,
b11001010 (
b1110110 !
b1110110 +
b1110110 '
1&
15
#890000
0&
05
#895000
b10000 4
b1001010110110110 3
b1001 /
b1001 #
b1001 1
b10010101 "
b10010101 ,
b10010101 (
b10110110 !
b10110110 +
b10110110 '
1&
15
#900000
0&
05
#905000
b10000 4
b10001000110 3
b100 /
b100 "
b100 ,
b100 (
b1000110 !
b1000110 +
b1000110 '
1&
15
#910000
0&
05
#915000
b10000 4
b110100111110111 3
b1011 /
b100 #
b100 1
b1101001 "
b1101001 ,
b1101001 (
b11110111 !
b11110111 +
b11110111 '
0*
1&
15
#920000
0&
05
#925000
b1011 #
b1011 1
1&
15
