sem3/sck/proj/TESTBENCH/simulation_modules.v
module global_signals 
    #(
        parameter SIM_CLOCK_CYCLES = 120,
        parameter CLOCK_PERIOD = 10,
        parameter SIGNAL_VCD_FILE = "SIGNALS.vcd"
    )
    (
        output wire o_CLK,
        output wire o_RSTn
    );
        
        reg clk;
        reg rst_n;

        assign o_CLK = clk;
        assign o_RSTn = rst_n;

        localparam CLK_PERIOD = CLOCK_PERIOD;
        always #(CLK_PERIOD/2) 
            clk=~clk;

        initial begin
            $dumpfile(SIGNAL_VCD_FILE);
            $dumpvars(0, testbench);
        end

        initial begin
            #1;
            rst_n<=1'bx; clk<=1'bx;
            
            #(CLK_PERIOD*3) rst_n<=1;
            
            #(CLK_PERIOD*3) rst_n<=0;clk<=0;
            
            repeat(5) 
                @(posedge clk);
            
            rst_n<=1;
            @(posedge clk);

            repeat(SIM_CLOCK_CYCLES) 
                @(posedge clk);

            $finish;
        end
endmodule

module random_vector
    #(
        parameter WIDTH = 9
    ) 
    (
        input  wire i_CLK,
        input  wire i_RSTn,
        input  wire i_READY,
        output wire o_VALID,
        output wire [WIDTH-1 : 0] o_Y
    );
        integer SEED = 100;
        reg s_was_valid;
        reg [WIDTH-1 : 0] s_Y;
        reg s_VALID;

        assign #(1) o_Y     = s_Y;
        assign #(1) o_VALID = s_VALID;

        initial 
        begin
            #1;
            @(posedge i_RSTn);

            s_Y <= {WIDTH{1'b0}};
            s_VALID <= 1'b0;
            s_was_valid <= 1'b0;

            forever 
            begin
                fork 
                    begin : GENEROWANIE_SYGNALOW_WYJSCIOWYCH
                        @(posedge i_CLK)
                        begin
                            s_VALID <= $random(SEED);
                            if (i_READY == 1'b1 && s_was_valid == 1'b1)
                                {s_Y} <= {s_Y, $random(SEED)};
                        end
                        
                        if (i_RSTn == 1'b0)
                            @(posedge i_RSTn);
                    end

                    begin : ZAPAMIETANIE_POPRZEDNIEGO_VALID
                        @(negedge i_CLK)
                            s_was_valid <= s_VALID;
                    end
                join
            end
        end
endmodule


module vector_data_accept 
#(
    parameter WIDTH = 8
)
(
        input wire i_CLK,
        input wire i_RSTn,
        input wire i_VALID,
        input wire [WIDTH-1 : 0] i_D,
        output wire o_READY
);

    integer SEED = 100;
    reg [WIDTH-1 : 0] s_DATA;
    reg s_READY;

    assign #(1) o_READY = s_READY;

    initial 
    begin
        #1;
        @(posedge i_RSTn);

        s_READY <= 1'b0;

        forever 
        begin
            @(posedge i_CLK)
            begin
                if (s_READY == 1'b1 && i_VALID == 1'b1) 
                        s_DATA <= i_D;
                s_READY <= $random(SEED);
            end
            
            if (i_RSTn == 1'b0)
            begin
                s_READY <= 1'b0;
                @(posedge i_RSTn);
            end

        end
    end

endmodule

sem3/sck/proj/MODEL/library_modules.v
module cpreg
#(
    parameter WIDTH = 4
)
(
    input wire i_CLK,
    input wire i_RSTn,
    input wire i_READY, i_VALID,
    output reg o_READY, o_VALID,
    input wire [WIDTH-1 : 0] i_D,
    output reg [WIDTH-1 : 0] o_Q   
);

    reg [WIDTH-1 : 0] s_Q1;
    reg s_LATCH, s_VALID;
    wire s_EN1, s_EN2;
    reg [1:0] s_state;

    localparam [1:0] 
        S0 = 2'b00, 
        S1 = 2'b01,
        S2 = 2'b11;

    assign s_EN1 = s_LATCH & (~ i_CLK);
    assign s_EN2 = s_LATCH & i_CLK;

    always @(posedge i_CLK or negedge i_RSTn)
        if (i_RSTn == 1'b0)
            s_VALID <= 1'b0;
        else
            s_VALID <= i_VALID;

    always @(s_EN1)
        if (s_EN1 == 1'b1)
            s_Q1 <= i_D;

    always @(s_EN2)
        if (s_EN2 == 1'b1)
            o_Q <= s_Q1;

    always @(posedge i_CLK or negedge i_RSTn)
        if(i_RSTn == 1'b0)
            s_state <= S0;
        else
            case(s_state)
                S0: if(i_VALID == 1'b1)
                        s_state <= S1;

                S1: if(i_READY == 1'b0)
                        s_state <= S2;
                    else
                        if(i_VALID == 1'b0)
                            s_state <= S0;

                S2: if(i_READY == 1'b1)
                        if(s_VALID)
                            s_state <= S1;
                        else
                            s_state <= S0;

                default:
                        s_state <= S0;
            endcase
        

    always @(*) 
    begin
        s_LATCH = 1'b1;
        o_READY = 1'b1;
        o_VALID = 1'b1;

        case (s_state)
            S0: begin
                    o_VALID = 1'b0;
                end
            S1: begin
                    if (i_READY == 1'b0)
                        s_LATCH = 1'b0;
                end

            S2: begin
                    s_LATCH = 1'b0;
                    o_READY = 1'b0;
                end
        endcase
    end

endmodule

sem3/sck/proj/MODEL/alu.v
`include "library_modules.v"

module ALU #(
    parameter WIDTH = 8
)
(
    input wire signed [WIDTH-1:0] i_arg0,
    input wire signed [WIDTH-1:0] i_arg1,
    input wire [1:0] i_oper,

    output wire [WIDTH+2:0] o_Y, 

    input wire i_CLK,
    input wire i_RSTn,
    input wire i_VALID,
    output wire o_READY,
    output wire o_VALID,
    input wire i_READY
);

    reg signed [WIDTH-1:0] o_result;
    reg flag_overflow;
    reg flag_carry;
    reg flag_zero;
    
    reg [WIDTH:0] temp_add_sub;
    reg [2*WIDTH-1:0] temp_vec;
    integer i;

    always @(*) begin
        o_result = {WIDTH{1'b0}};
        flag_overflow = 1'b0;
        flag_carry = 1'b0;
        flag_zero = 1'b0;
        temp_add_sub = {(WIDTH+1){1'b0}};

        case(i_oper)
           2'b00: begin
                temp_add_sub = i_arg0 + i_arg1; 
                
                o_result = temp_add_sub[WIDTH-1:0];
                
                flag_carry = temp_add_sub[WIDTH];

                flag_overflow = (i_arg0[WIDTH-1] == i_arg1[WIDTH-1]) && (o_result[WIDTH-1] != i_arg0[WIDTH-1]);
            end

            2'b01: begin
                {flag_carry, o_result} = $unsigned(i_arg0) - $unsigned(i_arg1);
                
                flag_overflow = (i_arg0[WIDTH-1] != i_arg1[WIDTH-1]) && (o_result[WIDTH-1] != i_arg0[WIDTH-1]);
            end

            2'b10: begin
                o_result = i_arg0 & i_arg1;
                flag_carry = 1'b0;
                flag_overflow = 1'b0;
            end

            2'b11: begin
                temp_vec = {i_arg1, i_arg0};
                o_result = 0;
                for(i = 0; i < 2*WIDTH; i = i + 1) begin
                    o_result = o_result + temp_vec[i];
                end
            end
        endcase

        flag_zero = (o_result == {WIDTH{1'b0}});
    end

    cpreg #(
        .WIDTH(WIDTH + 3)
    ) u_preg (
        .i_CLK(i_CLK),
        .i_RSTn(i_RSTn),
        .i_VALID(i_VALID),
        .o_READY(o_READY),
        
        .o_VALID(o_VALID),
        .i_READY(i_READY),
        
        .i_D({o_result, flag_overflow, flag_carry, flag_zero}),
        .o_Q(o_Y)
    );

endmodule

sem3/sck/proj/TESTBENCH/testbench.v
`timescale 1ns / 1ps
`include "simulation_modules.v"

module testbench;

    localparam DATA_WIDTH = 8;
    localparam OUT_WIDTH = DATA_WIDTH + 3;

    wire s_CLK, s_RSTn;
    wire s_alu_ready, s_alu_valid;
    wire [OUT_WIDTH-1:0] s_Y;

    reg [DATA_WIDTH-1:0] r_A, r_B;
    reg [1:0] r_oper;
    reg r_valid_in;
    reg r_ready_in;
    
    ALU #(.WIDTH(DATA_WIDTH)) UTOP 
    (
        .i_CLK(s_CLK),
        .i_RSTn(s_RSTn),
        .i_arg0(r_A), 
        .i_arg1(r_B),
        .i_oper(r_oper),
        .i_VALID(r_valid_in),
        .o_READY(s_alu_ready),
        .o_VALID(s_alu_valid),
        .i_READY(r_ready_in),
        .o_Y(s_Y)
    );

    global_signals #(.SIM_CLOCK_CYCLES(50), .CLOCK_PERIOD(10), .SIGNAL_VCD_FILE("alu_report.vcd"))
        U_RST_CLK (.o_CLK(s_CLK), .o_RSTn(s_RSTn));

    initial begin
        r_A = 0; r_B = 0; r_oper = 0;
        r_valid_in = 0;
        r_ready_in = 1;
        
        wait(s_RSTn == 0);
        wait(s_RSTn == 1);
        @(posedge s_CLK);

        @(posedge s_CLK);
        if(s_alu_ready) begin
            r_valid_in <= 1;
            r_oper <= 2'b00; // ADD
            r_A <= 8'd10;
            r_B <= 8'd5;
        end

        @(posedge s_CLK);
        if(s_alu_ready) begin
            r_valid_in <= 1;
            r_oper <= 2'b00; // ADD
            r_A <= 8'sd127;
            r_B <= 8'sd1;
        end

        @(posedge s_CLK);
        if(s_alu_ready) begin
            r_valid_in <= 1;
            r_oper <= 2'b01; // SUB
            r_A <= 8'd50;
            r_B <= 8'd50;
        end

        // 0xAA (10101010) & 0x0F (00001111) = 0x0A (00001010)
        @(posedge s_CLK);
        if(s_alu_ready) begin
            r_valid_in <= 1;
            r_oper <= 2'b10; // AND
            r_A <= 8'hAA;
            r_B <= 8'h0F;
        end

        // A=00000011 (3), B=00000001 (1)
        @(posedge s_CLK);
        if(s_alu_ready) begin
            r_valid_in <= 1;
            r_oper <= 2'b11;
            r_A <= 8'b00000011;
            r_B <= 8'b00000001;
        end

        @(posedge s_CLK);
        r_valid_in <= 0;

        repeat(5) @(posedge s_CLK);
    end

endmodule

sem3/sck/proj/WORK/alu_report.vcd
$date
	Wed Jan 07 01:48:03 2026
$end
$version
	Icarus Verilog
$end
$timescale
	1ps
$end
$scope module testbench $end
$var wire 1 ! s_alu_valid $end
$var wire 1 " s_alu_ready $end
$var wire 11 # s_Y [10:0] $end
$var wire 1 $ s_RSTn $end
$var wire 1 % s_CLK $end
$var reg 8 & r_A [7:0] $end
$var reg 8 ' r_B [7:0] $end
$var reg 2 ( r_oper [1:0] $end
$var reg 1 ) r_ready_in $end
$var reg 1 * r_valid_in $end
$scope module UTOP $end
$var wire 1 ) i_READY $end
$var wire 1 * i_VALID $end
$var wire 8 + i_arg0 [7:0] $end
$var wire 8 , i_arg1 [7:0] $end
$var wire 2 - i_oper [1:0] $end
$var wire 11 . o_Y [10:0] $end
$var wire 1 ! o_VALID $end
$var wire 1 " o_READY $end
$var wire 1 $ i_RSTn $end
$var wire 1 % i_CLK $end
$var reg 1 / flag_carry $end
$var reg 1 0 flag_overflow $end
$var reg 1 1 flag_zero $end
$var reg 8 2 o_result [7:0] $end
$var reg 9 3 temp_add_sub [8:0] $end
$var reg 16 4 temp_vec [15:0] $end
$var integer 32 5 i [31:0] $end
$scope module u_preg $end
$var wire 11 6 i_D [10:0] $end
$var wire 1 ) i_READY $end
$var wire 1 * i_VALID $end
$var wire 1 7 s_EN1 $end
$var wire 1 8 s_EN2 $end
$var wire 1 $ i_RSTn $end
$var wire 1 % i_CLK $end
$var reg 11 9 o_Q [10:0] $end
$var reg 1 " o_READY $end
$var reg 1 ! o_VALID $end
$var reg 1 : s_LATCH $end
$var reg 11 ; s_Q1 [10:0] $end
$var reg 1 < s_VALID $end
$var reg 2 = s_state [1:0] $end
$upscope $end
$upscope $end
$scope module U_RST_CLK $end
$var wire 1 % o_CLK $end
$var wire 1 $ o_RSTn $end
$var reg 1 % clk $end
$var reg 1 > rst_n $end
$upscope $end
$upscope $end
$enddefinitions $end
#0
$dumpvars
x>
bx =
x<
bx ;
1:
bx 9
x8
x7
b1 6
bx 5
bx 4
b0 3
b0 2
11
00
0/
bx .
b0 -
b0 ,
b0 +
0*
1)
b0 (
b0 '
b0 &
x%
x$
bx #
1"
1!
$end
#31000
1$
1>
#61000
0!
b1 ;
0<
b0 =
17
08
0%
0$
0>
#65000
b1 #
b1 .
b1 9
07
18
1%
#70000
17
08
0%
#75000
07
18
1%
#80000
17
08
0%
#85000
07
18
1%
#90000
17
08
0%
#95000
07
18
1%
#100000
17
08
0%
#105000
1$
1>
07
18
1%
#110000
17
08
0%
#115000
07
18
1%
#120000
17
08
0%
#125000
b1111 2
b1111 3
b1111000 6
01
b101 '
b101 ,
b1010 &
b1010 +
1*
07
18
1%
#130000
b1111000 ;
17
08
0%
#135000
10
b10000000 3
b10000000100 6
b10000000 2
1!
b1111000 #
b1111000 .
b1111000 9
b1 '
b1 ,
b1111111 &
b1111111 +
1<
b1 =
07
18
1%
#140000
b10000000100 ;
17
08
0%
#145000
11
b0 3
00
b1 6
b0 2
b10000000100 #
b10000000100 .
b10000000100 9
b110010 '
b110010 ,
b110010 &
b110010 +
b1 (
b1 -
07
18
1%
#150000
b1 ;
17
08
0%
#155000
b1010 2
b1010000 6
01
b1 #
b1 .
b1 9
b1111 '
b1111 ,
b10101010 &
b10101010 +
b10 (
b10 -
07
18
1%
#160000
b1010000 ;
17
08
0%
#165000
b10000 5
b100000011 4
b11000 6
b11 2
b1010000 #
b1010000 .
b1010000 9
b1 '
b1 ,
b11 &
b11 +
b11 (
b11 -
07
18
1%
#170000
b11000 ;
17
08
0%
#175000
b11000 #
b11000 .
b11000 9
0*
07
18
1%
#180000
17
08
0%
#185000
0!
b0 =
0<
07
18
1%
#190000
17
08
0%
#195000
07
18
1%
#200000
17
08
0%
#205000
07
18
1%
#210000
17
08
0%
#215000
07
18
1%
#220000
17
08
0%
#225000
07
18
1%
#230000
17
08
0%
#235000
07
18
1%
#240000
17
08
0%
#245000
07
18
1%
#250000
17
08
0%
#255000
07
18
1%
#260000
17
08
0%
#265000
07
18
1%
#270000
17
08
0%
#275000
07
18
1%
#280000
17
08
0%
#285000
07
18
1%
#290000
17
08
0%
#295000
07
18
1%
#300000
17
08
0%
#305000
07
18
1%
#310000
17
08
0%
#315000
07
18
1%
#320000
17
08
0%
#325000
07
18
1%
#330000
17
08
0%
#335000
07
18
1%
#340000
17
08
0%
#345000
07
18
1%
#350000
17
08
0%
#355000
07
18
1%
#360000
17
08
0%
#365000
07
18
1%
#370000
17
08
0%
#375000
07
18
1%
#380000
17
08
0%
#385000
07
18
1%
#390000
17
08
0%
#395000
07
18
1%
#400000
17
08
0%
#405000
07
18
1%
#410000
17
08
0%
#415000
07
18
1%
#420000
17
08
0%
#425000
07
18
1%
#430000
17
08
0%
#435000
07
18
1%
#440000
17
08
0%
#445000
07
18
1%
#450000
17
08
0%
#455000
07
18
1%
#460000
17
08
0%
#465000
07
18
1%
#470000
17
08
0%
#475000
07
18
1%
#480000
17
08
0%
#485000
07
18
1%
#490000
17
08
0%
#495000
07
18
1%
#500000
17
08
0%
#505000
07
18
1%
#510000
17
08
0%
#515000
07
18
1%
#520000
17
08
0%
#525000
07
18
1%
#530000
17
08
0%
#535000
07
18
1%
#540000
17
08
0%
#545000
07
18
1%
#550000
17
08
0%
#555000
07
18
1%
#560000
17
08
0%
#565000
07
18
1%
#570000
17
08
0%
#575000
07
18
1%
#580000
17
08
0%
#585000
07
18
1%
#590000
17
08
0%
#595000
07
18
1%
#600000
17
08
0%
#605000
07
18
1%
#610000
17
08
0%
#615000
07
18
1%
