sem3/sck/forRegs/MODEL/top.v
module REGS #(
    parameter N = 32,
    parameter M = 32,
    parameter ADDR_WIDTH = 5
)
(
    input wire i_clk,
    input wire i_rsn,

    input wire [ADDR_WIDTH-1:0] i_reg0,
    input wire [ADDR_WIDTH-1:0] i_reg1,

    input wire [ADDR_WIDTH-1:0] i_reg2,
    input wire [M-1:0] i_data2,

    output reg [M-1:0] o_data0,
    output reg [M-1:0] o_data1
);

    reg [M-1:0] RRR [1:N];
    integer i;

    always @(posedge i_clk or negedge i_rsn) begin
        if (!i_rsn) begin
            o_data0 <= {M{1'b0}};
            o_data1 <= {M{1'b0}};
            for (i = 1; i <= N; i = i + 1)
                RRR[i] <= {M{1'b0}};
        end 
        else begin
            if (i_reg2 > 0 && i_reg2 <= N)
                RRR[i_reg2] <= i_data2;

            o_data0 <= (i_reg0 > 0 && i_reg0 <= N) ? RRR[i_reg0] : {M{1'b0}};
            o_data1 <= (i_reg1 > 0 && i_reg1 <= N) ? RRR[i_reg1] : {M{1'b0}};
            
        end
    end

endmodule

sem3/sck/forAlu/TESTBENCH/simulation_modules.v
module global_signals 
    #(
        parameter SIM_CLOCK_CYCLES = 120,
        parameter CLOCK_PERIOD = 10,
        parameter SIGNAL_VCD_FILE = "SIGNALS.vcd"
    )
    (
        output wire o_CLK,
        output wire o_RSTn
    );
        
        reg clk;
        reg rst_n;

        assign o_CLK = clk;
        assign o_RSTn = rst_n;

        localparam CLK_PERIOD = CLOCK_PERIOD;
        always #(CLK_PERIOD/2) 
            clk=~clk;

        initial begin
            $dumpfile(SIGNAL_VCD_FILE);
            $dumpvars(0, testbench);
        end

        initial begin
            #1;
            rst_n<=1'bx; clk<=1'bx;
            
            #(CLK_PERIOD*3) rst_n<=1;
            
            #(CLK_PERIOD*3) rst_n<=0;clk<=0;
            
            repeat(5) 
                @(posedge clk);
            
            rst_n<=1;
            @(posedge clk);

            repeat(SIM_CLOCK_CYCLES) 
                @(posedge clk);

            $finish;
        end
endmodule

module random_vector
    #(
        parameter WIDTH = 9
    ) 
    (
        input  wire i_CLK,
        input  wire i_RSTn,
        input  wire i_READY,
        output wire o_VALID,
        output wire [WIDTH-1 : 0] o_Y
    );
        integer SEED = 100;
        reg s_was_valid;
        reg [WIDTH-1 : 0] s_Y;
        reg s_VALID;

        assign #(1) o_Y     = s_Y;
        assign #(1) o_VALID = s_VALID;

        initial 
        begin
            #1;
            @(posedge i_RSTn);

            s_Y <= {WIDTH{1'b0}};
            s_VALID <= 1'b0;
            s_was_valid <= 1'b0;

            forever 
            begin
                fork 
                    begin : GENEROWANIE_SYGNALOW_WYJSCIOWYCH
                        @(posedge i_CLK)
                        begin
                            s_VALID <= $random(SEED);
                            if (i_READY == 1'b1 && s_was_valid == 1'b1)
                                {s_Y} <= {s_Y, $random(SEED)};
                        end
                        
                        if (i_RSTn == 1'b0)
                            @(posedge i_RSTn);
                    end

                    begin : ZAPAMIETANIE_POPRZEDNIEGO_VALID
                        @(negedge i_CLK)
                            s_was_valid <= s_VALID;
                    end
                join
            end
        end
endmodule

sem3/sck/forRegs/TESTBENCH/testbench.v
`timescale 1ns / 1ps

module testbench;

    localparam N = 32;
    localparam M = 32;
    localparam ADDR_WIDTH = 5;

    wire s_clk, s_rsn;
    reg [ADDR_WIDTH-1:0] r_reg0, r_reg1, r_reg2;
    reg [M-1:0] r_data2;
    wire [M-1:0] w_data0, w_data1;

    global_signals #(.SIM_CLOCK_CYCLES(50), .CLOCK_PERIOD(10), .SIGNAL_VCD_FILE("regs_simulation.vcd"))
        U_RST_CLK (.o_CLK(s_clk), .o_RSTn(s_rsn));

    REGS #(
        .N(N),
        .M(M),
        .ADDR_WIDTH(ADDR_WIDTH)
    ) UTOP (
        .i_clk(s_clk),
        .i_rsn(s_rsn),
        .i_reg0(r_reg0),
        .i_reg1(r_reg1),
        .i_reg2(r_reg2),
        .i_data2(r_data2),
        .o_data0(w_data0),
        .o_data1(w_data1)
    );

    initial begin
        r_reg0 = 0;
        r_reg1 = 0;
        r_reg2 = 0;
        r_data2 = 0;

        wait(s_rsn == 0);
        wait(s_rsn == 1);
        @(posedge s_clk);

        $display("----------------------------------------------------------------");
        $display("Time\t\tAction\t\t\t\tR_Write\tData_W\t\tR_Read0\tData_R0");
        $display("----------------------------------------------------------------");

        // 1. Write to R2
        r_reg2 <= 2;
        r_data2 <= 32'hAABBCCDD;
        r_reg0 <= 0; 
        r_reg1 <= 0;
        @(posedge s_clk);
        #1 $display("%0t\tWrite R2=0x%h\t\t%0d\t%h\t%0d\t%h", $time, r_data2, r_reg2, r_data2, r_reg0, w_data0);

        // 2. Write to R5 and Read R2 (Previous write)
        r_reg2 <= 5;
        r_data2 <= 32'h11223344;
        r_reg0 <= 2; 
        @(posedge s_clk);
        #1 $display("%0t\tWrite R5 / Read R2\t\t%0d\t%h\t%0d\t%h", $time, r_data2, r_reg2, r_data2, r_reg0, w_data0);

        // 3. Read R5 (Previous write)
        r_reg2 <= 0; 
        r_data2 <= 0;
        r_reg0 <= 5; 
        @(posedge s_clk);
        #1 $display("%0t\tRead R5\t\t\t\t%0d\t%h\t%0d\t%h", $time, r_data2, r_reg2, r_data2, r_reg0, w_data0);

        // 4. Try Write to R0 (Should be ignored)
        r_reg2 <= 0; 
        r_data2 <= 32'hFFFFFFFF;
        r_reg0 <= 5; 
        @(posedge s_clk);
        #1 $display("%0t\tTry Write R0\t\t\t%0d\t%h\t%0d\t%h", $time, r_data2, r_reg2, r_data2, r_reg0, w_data0);

        // 5. Read R0 (Should be 0)
        r_reg2 <= 0;
        r_reg0 <= 0;
        @(posedge s_clk);
        #1 $display("%0t\tRead R0\t\t\t\t%0d\t%h\t%0d\t%h", $time, r_data2, r_reg2, r_data2, r_reg0, w_data0);

        // 6. Read Out of Bounds (Should be 0)
        r_reg0 <= 31; // Assuming N=32, this is valid. Let's try N+1
        r_reg1 <= 33; 
        @(posedge s_clk);
        #1 $display("%0t\tRead Invalid R33\t\t%0d\t%h\t%0d\t%h", $time, r_data2, r_reg2, r_data2, r_reg1, w_data1);

        repeat(5) @(posedge s_clk);
        $finish;
    end

endmodule

sem3/sck/forRegs/WORK/regs_simulation.vcd
$date
	Tue Jan 20 21:17:49 2026
$end
$version
	Icarus Verilog
$end
$timescale
	1ps
$end
$scope module testbench $end
$var wire 32 ! w_data1 [31:0] $end
$var wire 32 " w_data0 [31:0] $end
$var wire 1 # s_rsn $end
$var wire 1 $ s_clk $end
$var reg 32 % r_data2 [31:0] $end
$var reg 5 & r_reg0 [4:0] $end
$var reg 5 ' r_reg1 [4:0] $end
$var reg 5 ( r_reg2 [4:0] $end
$scope module UTOP $end
$var wire 32 ) i_data2 [31:0] $end
$var wire 5 * i_reg0 [4:0] $end
$var wire 5 + i_reg1 [4:0] $end
$var wire 5 , i_reg2 [4:0] $end
$var wire 1 # i_rsn $end
$var wire 1 $ i_clk $end
$var reg 32 - o_data0 [31:0] $end
$var reg 32 . o_data1 [31:0] $end
$var integer 32 / i [31:0] $end
$upscope $end
$scope module U_RST_CLK $end
$var wire 1 $ o_CLK $end
$var wire 1 # o_RSTn $end
$var reg 1 0 clk $end
$var reg 1 1 rst_n $end
$upscope $end
$upscope $end
$enddefinitions $end
#0
$dumpvars
x1
x0
bx /
bx .
bx -
b0 ,
b0 +
b0 *
b0 )
b0 (
b0 '
b0 &
b0 %
x$
x#
bx "
bx !
$end
#31000
1#
11
#61000
b0 !
b0 .
b0 "
b0 -
b100001 /
0$
00
0#
01
#65000
b100001 /
1$
10
#70000
0$
00
#75000
b100001 /
1$
10
#80000
0$
00
#85000
b100001 /
1$
10
#90000
0$
00
#95000
b100001 /
1$
10
#100000
0$
00
#105000
1#
11
b100001 /
1$
10
#110000
0$
00
#115000
b10101010101110111100110011011101 %
b10101010101110111100110011011101 )
b10 (
b10 ,
1$
10
#120000
0$
00
#125000
1$
10
#126000
b10 &
b10 *
b10001001000100011001101000100 %
b10001001000100011001101000100 )
b101 (
b101 ,
#130000
0$
00
#135000
b10101010101110111100110011011101 "
b10101010101110111100110011011101 -
1$
10
#136000
b101 &
b101 *
b0 %
b0 )
b0 (
b0 ,
#140000
0$
00
#145000
b10001001000100011001101000100 "
b10001001000100011001101000100 -
1$
10
#146000
b11111111111111111111111111111111 %
b11111111111111111111111111111111 )
#150000
0$
00
#155000
1$
10
#156000
b0 &
b0 *
#160000
0$
00
#165000
b0 "
b0 -
1$
10
#166000
b1 '
b1 +
b11111 &
b11111 *
